sw360/__init__.py
sw360/attachments.py
sw360/base.py
sw360/clearing.py
sw360/components.py
sw360/license.py
sw360/moderationrequests.py
sw360/packages.py
sw360/project.py
sw360/py.typed
sw360/releases.py
sw360/sw360_api.py
sw360/sw360error.py
sw360/sw360oauth2.py
sw360/vendor.py
sw360/vulnerabilities.py
sw360-1.10.1.dist-info/licenses/License.md
sw360-1.10.1.dist-info/licenses/LICENSES/MIT.txt
sw360-1.10.1.dist-info/METADATA
sw360-1.10.1.dist-info/WHEEL
sw360-1.10.1.dist-info/RECORD
