Metadata-Version: 2.4
Name: sw360
Version: 1.10.1
Summary: Python interface to the SW360 software component catalogue
License: MIT
License-File: LICENSES/MIT.txt
License-File: License.md
Author: Thomas Graf
Author-email: thomas.graf@siemens.com
Requires-Python: >=3.9,<4.0
Classifier: Development Status :: 5 - Production/Stable
Classifier: Environment :: Web Environment
Classifier: Intended Audience :: Developers
Classifier: License :: OSI Approved :: MIT License
Classifier: Natural Language :: English
Classifier: Operating System :: OS Independent
Classifier: Programming Language :: Python :: 3
Classifier: Programming Language :: Python :: 3.9
Classifier: Programming Language :: Python :: 3.10
Classifier: Programming Language :: Python :: 3.11
Classifier: Programming Language :: Python :: 3.12
Classifier: Programming Language :: Python :: 3.13
Classifier: Programming Language :: Python :: 3.14
Classifier: Programming Language :: Python :: 3 :: Only
Requires-Dist: requests (>=2.32.4,<3.0.0)
Project-URL: Homepage, https://github.com/sw360/sw360python
Project-URL: Repository, https://github.com/sw360/sw360python
